flask_monitoringdashboard/__init__.py
flask_monitoringdashboard/cli.py
flask_monitoringdashboard/constants.json
flask_monitoringdashboard/main.py
flask_monitoringdashboard/controllers/__init__.py
flask_monitoringdashboard/controllers/endpoints.py
flask_monitoringdashboard/controllers/exceptions.py
flask_monitoringdashboard/controllers/outliers.py
flask_monitoringdashboard/controllers/profiler.py
flask_monitoringdashboard/controllers/requests.py
flask_monitoringdashboard/controllers/versions.py
flask_monitoringdashboard/core/__init__.py
flask_monitoringdashboard/core/auth.py
flask_monitoringdashboard/core/blueprints.py
flask_monitoringdashboard/core/cache.py
flask_monitoringdashboard/core/colors.py
flask_monitoringdashboard/core/database_pruning.py
flask_monitoringdashboard/core/date_interval.py
flask_monitoringdashboard/core/get_ip.py
flask_monitoringdashboard/core/group_by.py
flask_monitoringdashboard/core/logger.py
flask_monitoringdashboard/core/measurement.py
flask_monitoringdashboard/core/rules.py
flask_monitoringdashboard/core/telemetry.py
flask_monitoringdashboard/core/timezone.py
flask_monitoringdashboard/core/utils.py
flask_monitoringdashboard/core/config/__init__.py
flask_monitoringdashboard/core/config/parser.py
flask_monitoringdashboard/core/custom_graph/__init__.py
flask_monitoringdashboard/core/exceptions/__init__.py
flask_monitoringdashboard/core/exceptions/exception_collector.py
flask_monitoringdashboard/core/exceptions/stack_frame_parsing.py
flask_monitoringdashboard/core/exceptions/stack_trace_hashing.py
flask_monitoringdashboard/core/exceptions/text_hash.py
flask_monitoringdashboard/core/profiler/__init__.py
flask_monitoringdashboard/core/profiler/base_profiler.py
flask_monitoringdashboard/core/profiler/outlier_profiler.py
flask_monitoringdashboard/core/profiler/performance_profiler.py
flask_monitoringdashboard/core/profiler/stacktrace_profiler.py
flask_monitoringdashboard/core/profiler/util/__init__.py
flask_monitoringdashboard-4.0.4.dist-info/licenses/LICENSE
flask_monitoringdashboard-4.0.4.dist-info/METADATA
flask_monitoringdashboard-4.0.4.dist-info/WHEEL
flask_monitoringdashboard-4.0.4.dist-info/entry_points.txt
flask_monitoringdashboard-4.0.4.dist-info/top_level.txt
flask_monitoringdashboard-4.0.4.dist-info/RECORD
